{
  "@context": "http://iiif.io/api/image/2/context.json",
  "@id": "http://0.0.0.0:4000/zine/img/derivatives/iiif/images/robotrhapsod_lp4uf753pl",
  "protocol": "http://iiif.io/api/image",
  "width": 2480,
  "height": 3509,
  "sizes": [
    {
      "width": 2480,
      "height": 3509
    },
    {
      "width": 250,
      "height": 354
    },
    {
      "width": 1140,
      "height": 1613
    }
  ],
  "profile": [
    "http://iiif.io/api/image/2/level0.json",
    {
      "supports": [
        "cors",
        "sizeByWhListed",
        "baseUriRedirect"
      ]
    }
  ],
  "tiles": [
    {
      "width": 512,
      "scaleFactors": [
        1,
        2,
        4,
        8
      ]
    }
  ]
}
